sciwriter/__init__.py
sciwriter/_compiler.py
sciwriter/_content.py
sciwriter/_jobs.py
sciwriter/_project.py
sciwriter/_writer.py
sciwriter/mcp_server.py
sciwriter/_analysis/__init__.py
sciwriter/_analysis/outline.py
sciwriter/_analysis/validation.py
sciwriter/_analysis/versions.py
sciwriter/_analysis/wordcount.py
sciwriter/_cli/__init__.py
sciwriter/_cli/__main__.py
sciwriter/_cli/analysis_cmds.py
sciwriter/_cli/citation_cmds.py
sciwriter/_cli/figure_cmds.py
sciwriter/_cli/info_cmds.py
sciwriter/_cli/jobs.py
sciwriter/_cli/main.py
sciwriter/_cli/mcp.py
sciwriter/_cli/media_cmds.py
sciwriter/_cli/ref_cmds.py
sciwriter/_cli/section_cmds.py
sciwriter/_cli/table_cmds.py
sciwriter/_cli/version_cmds.py
sciwriter/_mcp/__init__.py
sciwriter/_mcp/models.py
sciwriter/_mcp/handlers/__init__.py
sciwriter/_mcp/handlers/_utils.py
sciwriter/_mcp/handlers/citation_crud.py
sciwriter/_mcp/handlers/compile.py
sciwriter/_mcp/handlers/crud.py
sciwriter/_mcp/handlers/doc.py
sciwriter/_mcp/handlers/figure_crud.py
sciwriter/_mcp/handlers/inspection.py
sciwriter/_mcp/handlers/jobs.py
sciwriter/_mcp/handlers/project.py
sciwriter/_mcp/handlers/ref.py
sciwriter/_mcp/handlers/section_crud.py
sciwriter/_mcp/handlers/table_crud.py
sciwriter/_mcp/handlers/validation.py
sciwriter/_mcp/handlers/version.py
sciwriter/_mcp/tool_schemas/__init__.py
sciwriter/_mcp/tool_schemas/compile.py
sciwriter/_mcp/tool_schemas/crud.py
sciwriter/_mcp/tool_schemas/doc.py
sciwriter/_mcp/tool_schemas/jobs.py
sciwriter/_mcp/tool_schemas/project.py
sciwriter/_mcp/tool_schemas/ref.py
sciwriter/_mcp/tool_schemas/version.py
sciwriter/_media/__init__.py
sciwriter/_media/_utils.py
sciwriter/_media/citations.py
sciwriter/_media/figures.py
sciwriter/_media/references.py
sciwriter/_media/tables.py
sciwriter/templates/project/scripts/python/_logging.py
sciwriter/templates/project/scripts/python/check_cited_states.py
sciwriter/templates/project/scripts/python/compile_tex_structure.py
sciwriter-0.1.4.dist-info/METADATA
sciwriter-0.1.4.dist-info/WHEEL
sciwriter-0.1.4.dist-info/entry_points.txt
sciwriter-0.1.4.dist-info/licenses/LICENSE
sciwriter-0.1.4.dist-info/RECORD
